<TouchCollection>
	<Touch Type="multitouch-draganddrop" StartTargetX1="660" StartTargetY1="160" StopTargetX1="660" StopTargetY1="1092" StartTargetX2="160" StartTargetY2="160" StopTargetX2="160" StopTargetY2="1092">
		<Stroke>
			<Point X="616" Y="141" T="50" />
			<Point X="616" Y="142" T="69" />
			<Point X="616" Y="143" T="88" />
			<Point X="616" Y="144" T="107" />
			<Point X="616" Y="145" T="126" />
			<Point X="616" Y="147" T="145" />
			<Point X="616" Y="148" T="164" />
			<Point X="616" Y="149" T="182" />
			<Point X="616" Y="150" T="201" />
			<Point X="616" Y="151" T="221" />
			<Point X="616" Y="153" T="239" />
			<Point X="616" Y="154" T="258" />
			<Point X="616" Y="155" T="277" />
			<Point X="616" Y="155" T="296" />
			<Point X="616" Y="157" T="315" />
			<Point X="616" Y="158" T="333" />
			<Point X="616" Y="159" T="352" />
			<Point X="616" Y="161" T="372" />
			<Point X="616" Y="162" T="390" />
			<Point X="616" Y="164" T="409" />
			<Point X="616" Y="165" T="428" />
			<Point X="620" Y="167" T="447" />
			<Point X="620" Y="169" T="465" />
			<Point X="620" Y="171" T="484" />
			<Point X="620" Y="172" T="503" />
			<Point X="621" Y="174" T="522" />
			<Point X="621" Y="176" T="540" />
			<Point X="621" Y="179" T="559" />
			<Point X="622" Y="182" T="578" />
			<Point X="623" Y="185" T="597" />
			<Point X="623" Y="188" T="616" />
			<Point X="624" Y="192" T="635" />
			<Point X="624" Y="195" T="654" />
			<Point X="625" Y="199" T="672" />
			<Point X="626" Y="203" T="691" />
			<Point X="626" Y="205" T="710" />
			<Point X="626" Y="208" T="729" />
			<Point X="627" Y="212" T="748" />
			<Point X="627" Y="215" T="767" />
			<Point X="628" Y="219" T="785" />
			<Point X="628" Y="222" T="804" />
			<Point X="629" Y="225" T="822" />
			<Point X="629" Y="229" T="841" />
			<Point X="629" Y="232" T="860" />
			<Point X="630" Y="235" T="879" />
			<Point X="630" Y="236" T="898" />
			<Point X="630" Y="239" T="916" />
			<Point X="631" Y="242" T="935" />
			<Point X="631" Y="245" T="954" />
			<Point X="631" Y="249" T="973" />
			<Point X="632" Y="251" T="992" />
			<Point X="632" Y="254" T="1010" />
			<Point X="632" Y="257" T="1029" />
			<Point X="632" Y="260" T="1047" />
			<Point X="633" Y="263" T="1066" />
			<Point X="633" Y="265" T="1085" />
			<Point X="634" Y="269" T="1104" />
			<Point X="634" Y="273" T="1123" />
			<Point X="634" Y="277" T="1142" />
			<Point X="635" Y="281" T="1160" />
			<Point X="636" Y="286" T="1179" />
			<Point X="637" Y="291" T="1197" />
			<Point X="638" Y="298" T="1216" />
			<Point X="639" Y="304" T="1235" />
			<Point X="640" Y="311" T="1253" />
			<Point X="641" Y="314" T="1272" />
			<Point X="642" Y="319" T="1292" />
			<Point X="643" Y="325" T="1310" />
			<Point X="644" Y="332" T="1330" />
			<Point X="645" Y="339" T="1348" />
			<Point X="646" Y="344" T="1367" />
			<Point X="647" Y="349" T="1385" />
			<Point X="648" Y="355" T="1404" />
			<Point X="648" Y="360" T="1423" />
			<Point X="649" Y="365" T="1442" />
			<Point X="650" Y="371" T="1461" />
			<Point X="650" Y="373" T="1479" />
			<Point X="651" Y="378" T="1498" />
			<Point X="652" Y="384" T="1517" />
			<Point X="653" Y="391" T="1536" />
			<Point X="654" Y="397" T="1555" />
			<Point X="655" Y="404" T="1573" />
			<Point X="656" Y="411" T="1592" />
			<Point X="656" Y="416" T="1612" />
			<Point X="657" Y="421" T="1630" />
			<Point X="658" Y="426" T="1649" />
			<Point X="659" Y="431" T="1668" />
			<Point X="659" Y="434" T="1687" />
			<Point X="660" Y="438" T="1706" />
			<Point X="661" Y="445" T="1739" />
			<Point X="661" Y="448" T="1757" />
			<Point X="662" Y="449" T="1769" />
			<Point X="662" Y="451" T="1785" />
			<Point X="662" Y="455" T="1804" />
			<Point X="663" Y="458" T="1823" />
			<Point X="663" Y="462" T="1842" />
			<Point X="663" Y="466" T="1861" />
			<Point X="664" Y="469" T="1879" />
			<Point X="665" Y="473" T="1898" />
			<Point X="665" Y="477" T="1917" />
			<Point X="666" Y="482" T="1935" />
			<Point X="666" Y="485" T="1954" />
			<Point X="667" Y="488" T="1973" />
			<Point X="667" Y="493" T="1992" />
			<Point X="668" Y="499" T="2011" />
			<Point X="669" Y="504" T="2029" />
			<Point X="670" Y="509" T="2048" />
			<Point X="670" Y="515" T="2066" />
			<Point X="671" Y="520" T="2085" />
			<Point X="672" Y="526" T="2104" />
			<Point X="672" Y="531" T="2123" />
			<Point X="673" Y="536" T="2142" />
			<Point X="674" Y="539" T="2160" />
			<Point X="674" Y="541" T="2161" />
			<Point X="674" Y="544" T="2179" />
			<Point X="675" Y="549" T="2198" />
			<Point X="676" Y="554" T="2216" />
			<Point X="676" Y="558" T="2235" />
			<Point X="677" Y="561" T="2254" />
			<Point X="677" Y="565" T="2273" />
			<Point X="677" Y="568" T="2291" />
			<Point X="678" Y="571" T="2310" />
			<Point X="678" Y="573" T="2329" />
			<Point X="678" Y="576" T="2343" />
			<Point X="678" Y="578" T="2356" />
			<Point X="678" Y="580" T="2367" />
			<Point X="679" Y="583" T="2386" />
			<Point X="679" Y="587" T="2405" />
			<Point X="680" Y="590" T="2423" />
			<Point X="680" Y="593" T="2443" />
			<Point X="680" Y="597" T="2461" />
			<Point X="681" Y="600" T="2480" />
			<Point X="681" Y="604" T="2498" />
			<Point X="681" Y="608" T="2517" />
			<Point X="682" Y="611" T="2536" />
			<Point X="682" Y="613" T="2555" />
			<Point X="682" Y="617" T="2574" />
			<Point X="682" Y="621" T="2592" />
			<Point X="683" Y="625" T="2611" />
			<Point X="683" Y="630" T="2630" />
			<Point X="684" Y="635" T="2648" />
			<Point X="684" Y="641" T="2667" />
			<Point X="685" Y="646" T="2686" />
			<Point X="685" Y="650" T="2705" />
			<Point X="685" Y="652" T="2723" />
			<Point X="686" Y="658" T="2742" />
			<Point X="686" Y="661" T="2743" />
			<Point X="687" Y="664" T="2758" />
			<Point X="687" Y="667" T="2772" />
			<Point X="687" Y="673" T="2791" />
			<Point X="688" Y="678" T="2809" />
			<Point X="688" Y="683" T="2828" />
			<Point X="688" Y="689" T="2847" />
			<Point X="689" Y="694" T="2866" />
			<Point X="689" Y="700" T="2884" />
			<Point X="690" Y="705" T="2903" />
			<Point X="690" Y="710" T="2921" />
			<Point X="691" Y="714" T="2940" />
			<Point X="691" Y="716" T="2960" />
			<Point X="691" Y="718" T="2960" />
			<Point X="692" Y="720" T="2978" />
			<Point X="692" Y="725" T="2997" />
			<Point X="693" Y="730" T="3015" />
			<Point X="693" Y="734" T="3034" />
			<Point X="693" Y="738" T="3053" />
			<Point X="694" Y="742" T="3071" />
			<Point X="694" Y="745" T="3091" />
			<Point X="694" Y="749" T="3109" />
			<Point X="695" Y="753" T="3127" />
			<Point X="695" Y="755" T="3146" />
			<Point X="696" Y="759" T="3165" />
			<Point X="696" Y="763" T="3184" />
			<Point X="696" Y="767" T="3203" />
			<Point X="696" Y="770" T="3222" />
			<Point X="696" Y="774" T="3241" />
			<Point X="696" Y="778" T="3260" />
			<Point X="696" Y="781" T="3279" />
			<Point X="697" Y="785" T="3297" />
			<Point X="698" Y="789" T="3316" />
			<Point X="698" Y="792" T="3335" />
			<Point X="699" Y="794" T="3354" />
			<Point X="699" Y="798" T="3368" />
			<Point X="699" Y="800" T="3382" />
			<Point X="699" Y="801" T="3394" />
			<Point X="699" Y="805" T="3405" />
			<Point X="699" Y="807" T="3417" />
			<Point X="699" Y="809" T="3433" />
			<Point X="699" Y="810" T="3447" />
			<Point X="700" Y="812" T="3448" />
			<Point X="700" Y="815" T="3463" />
			<Point X="700" Y="817" T="3476" />
			<Point X="701" Y="819" T="3492" />
			<Point X="701" Y="823" T="3511" />
			<Point X="702" Y="826" T="3530" />
			<Point X="702" Y="830" T="3549" />
			<Point X="702" Y="833" T="3568" />
			<Point X="702" Y="837" T="3586" />
			<Point X="703" Y="840" T="3605" />
			<Point X="703" Y="843" T="3624" />
			<Point X="704" Y="847" T="3643" />
			<Point X="704" Y="850" T="3662" />
			<Point X="705" Y="854" T="3681" />
			<Point X="705" Y="858" T="3700" />
			<Point X="705" Y="859" T="3719" />
			<Point X="706" Y="863" T="3737" />
			<Point X="706" Y="867" T="3756" />
			<Point X="706" Y="870" T="3775" />
			<Point X="707" Y="874" T="3794" />
			<Point X="707" Y="877" T="3812" />
			<Point X="708" Y="881" T="3831" />
			<Point X="708" Y="885" T="3850" />
			<Point X="708" Y="889" T="3868" />
			<Point X="708" Y="893" T="3888" />
			<Point X="709" Y="894" T="3906" />
			<Point X="709" Y="898" T="3926" />
			<Point X="709" Y="902" T="3944" />
			<Point X="710" Y="905" T="3963" />
			<Point X="710" Y="909" T="3982" />
			<Point X="710" Y="913" T="4001" />
			<Point X="711" Y="917" T="4020" />
			<Point X="711" Y="920" T="4039" />
			<Point X="711" Y="926" T="4068" />
			<Point X="711" Y="929" T="4085" />
			<Point X="711" Y="931" T="4097" />
			<Point X="712" Y="933" T="4113" />
			<Point X="712" Y="936" T="4125" />
			<Point X="712" Y="938" T="4137" />
			<Point X="712" Y="940" T="4152" />
			<Point X="712" Y="944" T="4171" />
			<Point X="712" Y="949" T="4190" />
			<Point X="712" Y="953" T="4209" />
			<Point X="712" Y="957" T="4228" />
			<Point X="712" Y="961" T="4246" />
			<Point X="712" Y="965" T="4265" />
			<Point X="712" Y="971" T="4284" />
			<Point X="712" Y="977" T="4302" />
			<Point X="712" Y="984" T="4321" />
			<Point X="712" Y="988" T="4340" />
			<Point X="710" Y="995" T="4354" />
			<Point X="709" Y="998" T="4367" />
			<Point X="709" Y="1002" T="4380" />
			<Point X="708" Y="1009" T="4392" />
			<Point X="707" Y="1013" T="4403" />
			<Point X="706" Y="1017" T="4419" />
			<Point X="706" Y="1024" T="4438" />
			<Point X="705" Y="1029" T="4456" />
			<Point X="705" Y="1034" T="4475" />
			<Point X="704" Y="1039" T="4494" />
			<Point X="704" Y="1043" T="4513" />
			<Point X="703" Y="1047" T="4531" />
			<Point X="701" Y="1054" T="4562" />
			<Point X="700" Y="1058" T="4579" />
			<Point X="700" Y="1060" T="4591" />
			<Point X="699" Y="1061" T="4606" />
			<Point X="699" Y="1065" T="4625" />
			<Point X="698" Y="1069" T="4644" />
			<Point X="697" Y="1074" T="4663" />
			<Point X="696" Y="1079" T="4681" />
			<Point X="695" Y="1084" T="4700" />
			<Point X="694" Y="1089" T="4719" />
			<Point X="693" Y="1093" T="4738" />
			<Point X="692" Y="1098" T="4756" />
			<Point X="691" Y="1103" T="4775" />
			<Point X="691" Y="1106" T="4794" />
			<Point X="690" Y="1111" T="4810" />
			<Point X="689" Y="1116" T="4825" />
			<Point X="689" Y="1118" T="4836" />
			<Point X="689" Y="1120" T="4853" />
			<Point X="688" Y="1123" T="4872" />
			<Point X="687" Y="1127" T="4890" />
			<Point X="686" Y="1130" T="4910" />
			<Point X="684" Y="1133" T="4929" />
			<Point X="683" Y="1136" T="4948" />
			<Point X="683" Y="1138" T="4966" />
			<Point X="682" Y="1141" T="4985" />
			<Point X="681" Y="1143" T="5004" />
			<Point X="680" Y="1147" T="5032" />
			<Point X="679" Y="1148" T="5048" />
			<Point X="678" Y="1149" T="5061" />
			<Point X="678" Y="1150" T="5079" />
			<Point X="677" Y="1152" T="5097" />
			<Point X="677" Y="1153" T="5116" />
			<Point X="676" Y="1155" T="5135" />
			<Point X="675" Y="1156" T="5154" />
			<Point X="674" Y="1157" T="5173" />
			<Point X="673" Y="1158" T="5192" />
			<Point X="672" Y="1159" T="5211" />
			<Point X="671" Y="1159" T="5230" />
			<Point X="670" Y="1159" T="5248" />
			<Point X="669" Y="1159" T="5267" />
			<Point X="668" Y="1159" T="5286" />
			<Point X="668" Y="1159" T="5305" />
			<Point X="668" Y="1159" T="5323" />
			<Point X="667" Y="1159" T="5342" />
			<Point X="667" Y="1159" T="5361" />
			<Point X="667" Y="1159" T="5379" />
			<Point X="667" Y="1153" T="5399" />
			<Point X="670" Y="1151" T="5417" />
			<Point X="671" Y="1150" T="5436" />
			<Point X="672" Y="1149" T="5454" />
			<Point X="673" Y="1146" T="5482" />
			<Point X="673" Y="1144" T="5499" />
			<Point X="674" Y="1144" T="5511" />
			<Point X="674" Y="1143" T="5524" />
			<Point X="674" Y="1142" T="5544" />
			<Point X="675" Y="1142" T="5563" />
			<Point X="675" Y="1140" T="5582" />
			<Point X="675" Y="1139" T="5601" />
			<Point X="675" Y="1138" T="5620" />
			<Point X="676" Y="1136" T="5639" />
			<Point X="676" Y="1135" T="5658" />
			<Point X="677" Y="1133" T="5677" />
			<Point X="677" Y="1130" T="5696" />
			<Point X="677" Y="1127" T="5714" />
			<Point X="677" Y="1125" T="5733" />
			<Point X="677" Y="1123" T="5751" />
			<Point X="678" Y="1122" T="5770" />
			<Point X="678" Y="1119" T="5789" />
			<Point X="678" Y="1118" T="5808" />
			<Point X="679" Y="1116" T="5827" />
			<Point X="679" Y="1114" T="5846" />
			<Point X="679" Y="1112" T="5865" />
			<Point X="679" Y="1111" T="5879" />
			<Point X="679" Y="1109" T="5894" />
			<Point X="679" Y="1107" T="5911" />
			<Point X="679" Y="1106" T="5923" />
			<Point X="679" Y="1104" T="5940" />
			<Point X="679" Y="1103" T="5958" />
			<Point X="679" Y="1102" T="5978" />
			<Point X="679" Y="1102" T="6008" />
			<Point X="679" Y="1101" T="6027" />
			<Point X="680" Y="1101" T="6045" />
			<Point X="681" Y="1101" T="6097" />
			<Point X="681" Y="1101" T="6187" />
			<Point X="681" Y="1101" T="6393" />
			<Point X="681" Y="1101" T="6432" />
			<Point X="681" Y="1101" T="6451" />
			<Point X="675" Y="1101" T="6481" />
			<Point X="674" Y="1101" T="6500" />
			<Point X="673" Y="1100" T="6520" />
			<Point X="671" Y="1099" T="6540" />
			<Point X="670" Y="1098" T="6557" />
			<Point X="668" Y="1097" T="6575" />
			<Point X="666" Y="1095" T="6594" />
			<Point X="665" Y="1095" T="6609" />
			<Point X="663" Y="1093" T="6624" />
			<Point X="663" Y="1092" T="6641" />
		</Stroke>
		<Stroke>
			<Point X="185" Y="112" T="50" />
			<Point X="185" Y="112" T="69" />
			<Point X="185" Y="112" T="88" />
			<Point X="185" Y="112" T="107" />
			<Point X="185" Y="112" T="126" />
			<Point X="185" Y="112" T="145" />
			<Point X="185" Y="112" T="164" />
			<Point X="185" Y="112" T="182" />
			<Point X="185" Y="112" T="201" />
			<Point X="185" Y="112" T="221" />
			<Point X="185" Y="112" T="239" />
			<Point X="185" Y="112" T="258" />
			<Point X="185" Y="118" T="277" />
			<Point X="185" Y="120" T="296" />
			<Point X="185" Y="120" T="315" />
			<Point X="185" Y="122" T="333" />
			<Point X="185" Y="124" T="352" />
			<Point X="185" Y="126" T="372" />
			<Point X="185" Y="129" T="390" />
			<Point X="185" Y="131" T="409" />
			<Point X="185" Y="135" T="428" />
			<Point X="182" Y="137" T="447" />
			<Point X="181" Y="141" T="465" />
			<Point X="179" Y="146" T="484" />
			<Point X="178" Y="148" T="503" />
			<Point X="177" Y="155" T="522" />
			<Point X="175" Y="162" T="540" />
			<Point X="173" Y="167" T="559" />
			<Point X="173" Y="172" T="578" />
			<Point X="171" Y="176" T="597" />
			<Point X="170" Y="180" T="616" />
			<Point X="169" Y="183" T="635" />
			<Point X="168" Y="186" T="654" />
			<Point X="167" Y="189" T="672" />
			<Point X="166" Y="191" T="691" />
			<Point X="166" Y="193" T="710" />
			<Point X="165" Y="196" T="729" />
			<Point X="164" Y="199" T="748" />
			<Point X="163" Y="202" T="767" />
			<Point X="161" Y="205" T="785" />
			<Point X="160" Y="208" T="804" />
			<Point X="159" Y="211" T="822" />
			<Point X="158" Y="214" T="841" />
			<Point X="157" Y="217" T="860" />
			<Point X="156" Y="220" T="879" />
			<Point X="156" Y="222" T="898" />
			<Point X="154" Y="226" T="916" />
			<Point X="153" Y="231" T="935" />
			<Point X="151" Y="237" T="954" />
			<Point X="149" Y="243" T="973" />
			<Point X="147" Y="249" T="992" />
			<Point X="146" Y="256" T="1010" />
			<Point X="145" Y="262" T="1029" />
			<Point X="143" Y="269" T="1047" />
			<Point X="142" Y="275" T="1066" />
			<Point X="141" Y="277" T="1085" />
			<Point X="140" Y="282" T="1104" />
			<Point X="139" Y="287" T="1123" />
			<Point X="137" Y="293" T="1142" />
			<Point X="136" Y="298" T="1160" />
			<Point X="135" Y="302" T="1179" />
			<Point X="134" Y="307" T="1197" />
			<Point X="133" Y="310" T="1216" />
			<Point X="132" Y="313" T="1235" />
			<Point X="132" Y="317" T="1253" />
			<Point X="132" Y="318" T="1272" />
			<Point X="131" Y="322" T="1292" />
			<Point X="130" Y="326" T="1310" />
			<Point X="129" Y="329" T="1330" />
			<Point X="128" Y="333" T="1348" />
			<Point X="127" Y="337" T="1367" />
			<Point X="126" Y="341" T="1385" />
			<Point X="125" Y="345" T="1404" />
			<Point X="124" Y="350" T="1423" />
			<Point X="123" Y="355" T="1442" />
			<Point X="122" Y="360" T="1461" />
			<Point X="122" Y="362" T="1479" />
			<Point X="121" Y="366" T="1498" />
			<Point X="120" Y="370" T="1517" />
			<Point X="119" Y="375" T="1536" />
			<Point X="118" Y="381" T="1555" />
			<Point X="117" Y="388" T="1573" />
			<Point X="116" Y="394" T="1592" />
			<Point X="116" Y="401" T="1612" />
			<Point X="115" Y="408" T="1630" />
			<Point X="113" Y="415" T="1649" />
			<Point X="112" Y="422" T="1668" />
			<Point X="112" Y="425" T="1687" />
			<Point X="111" Y="430" T="1706" />
			<Point X="109" Y="440" T="1739" />
			<Point X="109" Y="445" T="1757" />
			<Point X="108" Y="448" T="1769" />
			<Point X="108" Y="450" T="1785" />
			<Point X="107" Y="455" T="1804" />
			<Point X="106" Y="460" T="1823" />
			<Point X="106" Y="463" T="1842" />
			<Point X="105" Y="468" T="1861" />
			<Point X="104" Y="474" T="1879" />
			<Point X="103" Y="479" T="1898" />
			<Point X="103" Y="484" T="1917" />
			<Point X="102" Y="489" T="1935" />
			<Point X="101" Y="494" T="1954" />
			<Point X="100" Y="497" T="1973" />
			<Point X="99" Y="502" T="1992" />
			<Point X="99" Y="509" T="2011" />
			<Point X="98" Y="514" T="2029" />
			<Point X="97" Y="520" T="2048" />
			<Point X="96" Y="524" T="2066" />
			<Point X="96" Y="529" T="2085" />
			<Point X="95" Y="533" T="2104" />
			<Point X="94" Y="539" T="2123" />
			<Point X="94" Y="544" T="2142" />
			<Point X="93" Y="547" T="2160" />
			<Point X="93" Y="549" T="2161" />
			<Point X="93" Y="551" T="2179" />
			<Point X="92" Y="556" T="2198" />
			<Point X="92" Y="560" T="2216" />
			<Point X="91" Y="564" T="2235" />
			<Point X="91" Y="568" T="2254" />
			<Point X="91" Y="572" T="2273" />
			<Point X="91" Y="576" T="2291" />
			<Point X="91" Y="581" T="2310" />
			<Point X="90" Y="583" T="2329" />
			<Point X="90" Y="587" T="2343" />
			<Point X="90" Y="589" T="2356" />
			<Point X="90" Y="592" T="2367" />
			<Point X="90" Y="600" T="2386" />
			<Point X="90" Y="608" T="2405" />
			<Point X="90" Y="615" T="2423" />
			<Point X="90" Y="622" T="2443" />
			<Point X="89" Y="629" T="2461" />
			<Point X="89" Y="635" T="2480" />
			<Point X="88" Y="640" T="2498" />
			<Point X="88" Y="645" T="2517" />
			<Point X="87" Y="649" T="2536" />
			<Point X="87" Y="650" T="2555" />
			<Point X="87" Y="653" T="2574" />
			<Point X="87" Y="657" T="2592" />
			<Point X="87" Y="660" T="2611" />
			<Point X="87" Y="664" T="2630" />
			<Point X="87" Y="668" T="2648" />
			<Point X="87" Y="672" T="2667" />
			<Point X="86" Y="676" T="2686" />
			<Point X="86" Y="682" T="2705" />
			<Point X="86" Y="685" T="2723" />
			<Point X="86" Y="692" T="2742" />
			<Point X="86" Y="696" T="2743" />
			<Point X="86" Y="700" T="2758" />
			<Point X="86" Y="704" T="2772" />
			<Point X="86" Y="710" T="2791" />
			<Point X="86" Y="716" T="2809" />
			<Point X="85" Y="723" T="2828" />
			<Point X="85" Y="728" T="2847" />
			<Point X="85" Y="733" T="2866" />
			<Point X="85" Y="737" T="2884" />
			<Point X="85" Y="741" T="2903" />
			<Point X="85" Y="744" T="2921" />
			<Point X="85" Y="748" T="2940" />
			<Point X="85" Y="749" T="2960" />
			<Point X="85" Y="751" T="2960" />
			<Point X="85" Y="753" T="2978" />
			<Point X="85" Y="758" T="2997" />
			<Point X="85" Y="762" T="3015" />
			<Point X="85" Y="766" T="3034" />
			<Point X="85" Y="770" T="3053" />
			<Point X="85" Y="774" T="3071" />
			<Point X="85" Y="778" T="3091" />
			<Point X="85" Y="783" T="3109" />
			<Point X="85" Y="789" T="3127" />
			<Point X="85" Y="792" T="3146" />
			<Point X="85" Y="797" T="3165" />
			<Point X="85" Y="802" T="3184" />
			<Point X="85" Y="805" T="3203" />
			<Point X="85" Y="809" T="3222" />
			<Point X="85" Y="813" T="3241" />
			<Point X="85" Y="817" T="3260" />
			<Point X="85" Y="821" T="3279" />
			<Point X="85" Y="825" T="3297" />
			<Point X="85" Y="829" T="3316" />
			<Point X="85" Y="832" T="3335" />
			<Point X="85" Y="834" T="3354" />
			<Point X="85" Y="837" T="3368" />
			<Point X="85" Y="838" T="3382" />
			<Point X="85" Y="840" T="3394" />
			<Point X="85" Y="843" T="3405" />
			<Point X="85" Y="844" T="3417" />
			<Point X="85" Y="845" T="3433" />
			<Point X="85" Y="847" T="3447" />
			<Point X="85" Y="848" T="3448" />
			<Point X="85" Y="851" T="3463" />
			<Point X="85" Y="853" T="3476" />
			<Point X="85" Y="854" T="3492" />
			<Point X="85" Y="858" T="3511" />
			<Point X="85" Y="861" T="3530" />
			<Point X="85" Y="864" T="3549" />
			<Point X="85" Y="868" T="3568" />
			<Point X="85" Y="872" T="3586" />
			<Point X="85" Y="876" T="3605" />
			<Point X="85" Y="882" T="3624" />
			<Point X="85" Y="888" T="3643" />
			<Point X="85" Y="893" T="3662" />
			<Point X="85" Y="897" T="3681" />
			<Point X="85" Y="901" T="3700" />
			<Point X="85" Y="902" T="3719" />
			<Point X="85" Y="906" T="3737" />
			<Point X="85" Y="910" T="3756" />
			<Point X="85" Y="914" T="3775" />
			<Point X="85" Y="918" T="3794" />
			<Point X="85" Y="922" T="3812" />
			<Point X="85" Y="925" T="3831" />
			<Point X="85" Y="928" T="3850" />
			<Point X="85" Y="931" T="3868" />
			<Point X="85" Y="934" T="3888" />
			<Point X="85" Y="936" T="3906" />
			<Point X="85" Y="939" T="3926" />
			<Point X="85" Y="941" T="3944" />
			<Point X="85" Y="944" T="3963" />
			<Point X="85" Y="947" T="3982" />
			<Point X="85" Y="950" T="4001" />
			<Point X="85" Y="954" T="4020" />
			<Point X="85" Y="957" T="4039" />
			<Point X="85" Y="961" T="4068" />
			<Point X="85" Y="964" T="4085" />
			<Point X="85" Y="965" T="4097" />
			<Point X="85" Y="967" T="4113" />
			<Point X="85" Y="969" T="4125" />
			<Point X="85" Y="970" T="4137" />
			<Point X="85" Y="971" T="4152" />
			<Point X="85" Y="974" T="4171" />
			<Point X="85" Y="976" T="4190" />
			<Point X="85" Y="979" T="4209" />
			<Point X="85" Y="982" T="4228" />
			<Point X="85" Y="985" T="4246" />
			<Point X="85" Y="988" T="4265" />
			<Point X="85" Y="991" T="4284" />
			<Point X="85" Y="994" T="4302" />
			<Point X="85" Y="996" T="4321" />
			<Point X="85" Y="997" T="4340" />
			<Point X="88" Y="1000" T="4354" />
			<Point X="88" Y="1001" T="4367" />
			<Point X="88" Y="1002" T="4380" />
			<Point X="89" Y="1005" T="4392" />
			<Point X="89" Y="1006" T="4403" />
			<Point X="89" Y="1008" T="4419" />
			<Point X="90" Y="1011" T="4438" />
			<Point X="91" Y="1014" T="4456" />
			<Point X="92" Y="1018" T="4475" />
			<Point X="93" Y="1022" T="4494" />
			<Point X="95" Y="1026" T="4513" />
			<Point X="96" Y="1031" T="4531" />
			<Point X="99" Y="1038" T="4562" />
			<Point X="101" Y="1043" T="4579" />
			<Point X="101" Y="1045" T="4591" />
			<Point X="102" Y="1047" T="4606" />
			<Point X="104" Y="1051" T="4625" />
			<Point X="105" Y="1055" T="4644" />
			<Point X="107" Y="1058" T="4663" />
			<Point X="108" Y="1061" T="4681" />
			<Point X="109" Y="1063" T="4700" />
			<Point X="111" Y="1066" T="4719" />
			<Point X="112" Y="1068" T="4738" />
			<Point X="113" Y="1070" T="4756" />
			<Point X="114" Y="1073" T="4775" />
			<Point X="115" Y="1074" T="4794" />
			<Point X="116" Y="1077" T="4810" />
			<Point X="117" Y="1080" T="4825" />
			<Point X="117" Y="1081" T="4836" />
			<Point X="117" Y="1082" T="4853" />
			<Point X="118" Y="1084" T="4872" />
			<Point X="119" Y="1086" T="4890" />
			<Point X="120" Y="1088" T="4910" />
			<Point X="121" Y="1090" T="4929" />
			<Point X="122" Y="1092" T="4948" />
			<Point X="123" Y="1094" T="4966" />
			<Point X="124" Y="1095" T="4985" />
			<Point X="125" Y="1097" T="5004" />
			<Point X="127" Y="1099" T="5032" />
			<Point X="128" Y="1099" T="5048" />
			<Point X="129" Y="1100" T="5061" />
			<Point X="129" Y="1101" T="5079" />
			<Point X="130" Y="1102" T="5097" />
			<Point X="132" Y="1104" T="5116" />
			<Point X="132" Y="1105" T="5135" />
			<Point X="133" Y="1105" T="5154" />
			<Point X="134" Y="1106" T="5173" />
			<Point X="135" Y="1107" T="5192" />
			<Point X="136" Y="1108" T="5211" />
			<Point X="136" Y="1108" T="5230" />
			<Point X="138" Y="1110" T="5248" />
			<Point X="138" Y="1110" T="5267" />
			<Point X="139" Y="1111" T="5286" />
			<Point X="140" Y="1112" T="5305" />
			<Point X="141" Y="1112" T="5323" />
			<Point X="141" Y="1112" T="5342" />
			<Point X="142" Y="1113" T="5361" />
			<Point X="143" Y="1114" T="5379" />
			<Point X="143" Y="1114" T="5399" />
			<Point X="144" Y="1115" T="5417" />
			<Point X="144" Y="1115" T="5436" />
			<Point X="145" Y="1116" T="5454" />
			<Point X="146" Y="1117" T="5482" />
			<Point X="146" Y="1117" T="5499" />
			<Point X="147" Y="1118" T="5511" />
			<Point X="147" Y="1118" T="5524" />
			<Point X="148" Y="1119" T="5544" />
			<Point X="148" Y="1119" T="5563" />
			<Point X="148" Y="1119" T="5582" />
			<Point X="149" Y="1120" T="5601" />
			<Point X="149" Y="1120" T="5620" />
			<Point X="150" Y="1120" T="5639" />
			<Point X="150" Y="1121" T="5658" />
			<Point X="150" Y="1121" T="5677" />
			<Point X="151" Y="1121" T="5696" />
			<Point X="151" Y="1122" T="5714" />
			<Point X="151" Y="1122" T="5733" />
			<Point X="152" Y="1122" T="5751" />
			<Point X="152" Y="1122" T="5770" />
			<Point X="152" Y="1122" T="5789" />
			<Point X="152" Y="1123" T="5808" />
			<Point X="152" Y="1123" T="5827" />
			<Point X="153" Y="1123" T="5846" />
			<Point X="153" Y="1124" T="5865" />
			<Point X="153" Y="1124" T="5879" />
			<Point X="153" Y="1124" T="5894" />
			<Point X="153" Y="1125" T="5911" />
			<Point X="153" Y="1125" T="5923" />
			<Point X="153" Y="1125" T="5940" />
			<Point X="153" Y="1126" T="5958" />
			<Point X="153" Y="1126" T="5978" />
			<Point X="154" Y="1127" T="6008" />
			<Point X="154" Y="1127" T="6027" />
			<Point X="154" Y="1127" T="6045" />
			<Point X="154" Y="1128" T="6097" />
			<Point X="155" Y="1129" T="6187" />
			<Point X="156" Y="1129" T="6393" />
			<Point X="157" Y="1129" T="6432" />
			<Point X="157" Y="1123" T="6451" />
			<Point X="157" Y="1123" T="6481" />
			<Point X="158" Y="1122" T="6500" />
			<Point X="158" Y="1121" T="6520" />
			<Point X="158" Y="1121" T="6540" />
			<Point X="158" Y="1120" T="6557" />
			<Point X="158" Y="1119" T="6575" />
			<Point X="158" Y="1118" T="6594" />
			<Point X="158" Y="1117" T="6609" />
			<Point X="158" Y="1117" T="6624" />
			<Point X="158" Y="1117" T="6641" />
		</Stroke>
	</Touch>
</TouchCollection>
