<TouchCollection>
	<Touch Type="singletouch-draganddrop" StartTargetX="75" StartTargetY="75" StopTargetX="245" StopTargetY="305">
		<Stroke>
			<Point X="74" Y="72" T="237" />
			<Point X="74" Y="73" T="255" />
			<Point X="74" Y="74" T="274" />
			<Point X="74" Y="75" T="294" />
			<Point X="75" Y="76" T="315" />
			<Point X="76" Y="77" T="337" />
			<Point X="76" Y="78" T="355" />
			<Point X="76" Y="79" T="375" />
			<Point X="77" Y="80" T="396" />
			<Point X="77" Y="81" T="415" />
			<Point X="77" Y="82" T="436" />
			<Point X="77" Y="83" T="456" />
			<Point X="78" Y="84" T="477" />
			<Point X="78" Y="85" T="516" />
			<Point X="79" Y="85" T="538" />
			<Point X="79" Y="86" T="557" />
			<Point X="79" Y="87" T="577" />
			<Point X="79" Y="88" T="597" />
			<Point X="80" Y="89" T="639" />
			<Point X="81" Y="90" T="680" />
			<Point X="81" Y="91" T="717" />
			<Point X="82" Y="92" T="758" />
			<Point X="83" Y="93" T="798" />
			<Point X="84" Y="93" T="817" />
			<Point X="84" Y="94" T="837" />
			<Point X="85" Y="95" T="858" />
			<Point X="85" Y="96" T="878" />
			<Point X="86" Y="97" T="898" />
			<Point X="86" Y="98" T="918" />
			<Point X="87" Y="98" T="997" />
			<Point X="87" Y="99" T="1018" />
			<Point X="88" Y="100" T="1039" />
			<Point X="89" Y="100" T="1099" />
			<Point X="89" Y="101" T="1139" />
			<Point X="90" Y="102" T="1198" />
			<Point X="90" Y="103" T="1217" />
			<Point X="90" Y="104" T="1279" />
			<Point X="91" Y="104" T="1297" />
			<Point X="91" Y="105" T="1338" />
			<Point X="92" Y="105" T="1356" />
			<Point X="92" Y="106" T="1377" />
			<Point X="93" Y="106" T="1416" />
			<Point X="93" Y="107" T="1459" />
			<Point X="94" Y="108" T="1498" />
			<Point X="94" Y="109" T="1540" />
			<Point X="95" Y="109" T="1557" />
			<Point X="95" Y="110" T="1598" />
			<Point X="96" Y="111" T="1679" />
			<Point X="97" Y="112" T="1759" />
			<Point X="97" Y="113" T="1795" />
			<Point X="98" Y="113" T="1814" />
			<Point X="98" Y="114" T="1834" />
			<Point X="98" Y="115" T="1874" />
			<Point X="99" Y="115" T="1916" />
			<Point X="99" Y="116" T="1954" />
			<Point X="100" Y="116" T="1997" />
			<Point X="100" Y="117" T="2075" />
			<Point X="100" Y="118" T="2113" />
			<Point X="101" Y="118" T="2154" />
			<Point X="101" Y="119" T="2253" />
			<Point X="101" Y="120" T="2293" />
			<Point X="101" Y="121" T="2338" />
			<Point X="102" Y="121" T="2355" />
			<Point X="102" Y="122" T="2371" />
			<Point X="102" Y="123" T="2431" />
			<Point X="103" Y="123" T="2453" />
			<Point X="103" Y="124" T="2471" />
			<Point X="103" Y="125" T="2513" />
			<Point X="103" Y="126" T="2531" />
			<Point X="104" Y="127" T="2571" />
			<Point X="104" Y="128" T="2595" />
			<Point X="104" Y="129" T="2631" />
			<Point X="105" Y="130" T="2653" />
			<Point X="106" Y="130" T="2672" />
			<Point X="106" Y="131" T="2694" />
			<Point X="107" Y="132" T="2732" />
			<Point X="107" Y="133" T="2753" />
			<Point X="108" Y="134" T="2792" />
			<Point X="108" Y="135" T="2814" />
			<Point X="109" Y="136" T="2852" />
			<Point X="109" Y="137" T="2874" />
			<Point X="110" Y="137" T="2894" />
			<Point X="110" Y="138" T="2913" />
			<Point X="110" Y="139" T="2933" />
			<Point X="111" Y="140" T="2953" />
			<Point X="112" Y="140" T="2974" />
			<Point X="112" Y="141" T="2994" />
			<Point X="113" Y="142" T="3016" />
			<Point X="114" Y="143" T="3054" />
			<Point X="114" Y="144" T="3076" />
			<Point X="115" Y="145" T="3095" />
			<Point X="116" Y="146" T="3115" />
			<Point X="116" Y="147" T="3135" />
			<Point X="116" Y="148" T="3155" />
			<Point X="117" Y="149" T="3175" />
			<Point X="118" Y="150" T="3196" />
			<Point X="119" Y="151" T="3216" />
			<Point X="119" Y="152" T="3236" />
			<Point X="120" Y="153" T="3259" />
			<Point X="121" Y="154" T="3277" />
			<Point X="122" Y="155" T="3297" />
			<Point X="122" Y="156" T="3317" />
			<Point X="123" Y="157" T="3338" />
			<Point X="124" Y="158" T="3361" />
			<Point X="124" Y="159" T="3378" />
			<Point X="124" Y="160" T="3398" />
			<Point X="125" Y="161" T="3419" />
			<Point X="126" Y="162" T="3439" />
			<Point X="126" Y="163" T="3462" />
			<Point X="127" Y="164" T="3479" />
			<Point X="128" Y="165" T="3500" />
			<Point X="129" Y="166" T="3520" />
			<Point X="130" Y="167" T="3540" />
			<Point X="131" Y="168" T="3563" />
			<Point X="132" Y="169" T="3581" />
			<Point X="133" Y="170" T="3601" />
			<Point X="134" Y="171" T="3621" />
			<Point X="134" Y="172" T="3641" />
			<Point X="135" Y="173" T="3664" />
			<Point X="136" Y="174" T="3682" />
			<Point X="136" Y="175" T="3702" />
			<Point X="137" Y="176" T="3722" />
			<Point X="138" Y="178" T="3742" />
			<Point X="139" Y="180" T="3764" />
			<Point X="140" Y="181" T="3783" />
			<Point X="141" Y="182" T="3803" />
			<Point X="142" Y="184" T="3824" />
			<Point X="143" Y="185" T="3844" />
			<Point X="144" Y="186" T="3865" />
			<Point X="145" Y="187" T="3885" />
			<Point X="146" Y="188" T="3905" />
			<Point X="146" Y="189" T="3925" />
			<Point X="147" Y="190" T="3945" />
			<Point X="148" Y="191" T="3965" />
			<Point X="149" Y="192" T="3985" />
			<Point X="150" Y="193" T="4008" />
			<Point X="150" Y="194" T="4026" />
			<Point X="151" Y="195" T="4046" />
			<Point X="152" Y="196" T="4067" />
			<Point X="152" Y="197" T="4087" />
			<Point X="153" Y="198" T="4110" />
			<Point X="154" Y="199" T="4127" />
			<Point X="154" Y="200" T="4148" />
			<Point X="155" Y="201" T="4168" />
			<Point X="155" Y="202" T="4188" />
			<Point X="156" Y="203" T="4211" />
			<Point X="157" Y="204" T="4229" />
			<Point X="158" Y="205" T="4249" />
			<Point X="158" Y="206" T="4269" />
			<Point X="159" Y="207" T="4289" />
			<Point X="160" Y="208" T="4312" />
			<Point X="161" Y="209" T="4330" />
			<Point X="162" Y="210" T="4350" />
			<Point X="162" Y="211" T="4370" />
			<Point X="162" Y="212" T="4391" />
			<Point X="163" Y="213" T="4414" />
			<Point X="164" Y="214" T="4431" />
			<Point X="165" Y="215" T="4451" />
			<Point X="166" Y="215" T="4472" />
			<Point X="167" Y="216" T="4492" />
			<Point X="168" Y="217" T="4513" />
			<Point X="169" Y="218" T="4552" />
			<Point X="170" Y="219" T="4574" />
			<Point X="171" Y="220" T="4612" />
			<Point X="172" Y="220" T="4634" />
			<Point X="173" Y="221" T="4652" />
			<Point X="174" Y="221" T="4673" />
			<Point X="175" Y="222" T="4695" />
			<Point X="176" Y="223" T="4725" />
			<Point X="177" Y="224" T="4742" />
			<Point X="178" Y="225" T="4766" />
			<Point X="184" Y="229" T="4783" />
			<Point X="188" Y="233" T="4798" />
			<Point X="189" Y="234" T="4815" />
			<Point X="194" Y="238" T="4835" />
			<Point X="195" Y="238" T="4855" />
			<Point X="196" Y="239" T="4877" />
			<Point X="200" Y="240" T="4896" />
			<Point X="201" Y="241" T="4916" />
			<Point X="202" Y="242" T="4936" />
			<Point X="203" Y="243" T="4956" />
			<Point X="204" Y="244" T="4976" />
			<Point X="205" Y="245" T="4997" />
			<Point X="206" Y="246" T="5020" />
			<Point X="207" Y="247" T="5037" />
			<Point X="208" Y="248" T="5057" />
			<Point X="209" Y="249" T="5078" />
			<Point X="210" Y="250" T="5098" />
			<Point X="211" Y="251" T="5121" />
			<Point X="212" Y="252" T="5138" />
			<Point X="213" Y="253" T="5159" />
			<Point X="214" Y="254" T="5179" />
			<Point X="215" Y="255" T="5199" />
			<Point X="215" Y="256" T="5222" />
			<Point X="216" Y="257" T="5240" />
			<Point X="217" Y="258" T="5260" />
			<Point X="218" Y="259" T="5280" />
			<Point X="219" Y="260" T="5300" />
			<Point X="220" Y="261" T="5323" />
			<Point X="221" Y="262" T="5341" />
			<Point X="222" Y="263" T="5361" />
			<Point X="223" Y="265" T="5381" />
			<Point X="224" Y="266" T="5401" />
			<Point X="226" Y="268" T="5424" />
			<Point X="228" Y="270" T="5442" />
			<Point X="229" Y="271" T="5462" />
			<Point X="230" Y="272" T="5483" />
			<Point X="231" Y="273" T="5503" />
			<Point X="233" Y="274" T="5524" />
			<Point X="234" Y="275" T="5543" />
			<Point X="235" Y="276" T="5563" />
			<Point X="236" Y="277" T="5584" />
			<Point X="237" Y="278" T="5604" />
			<Point X="238" Y="279" T="5626" />
			<Point X="239" Y="280" T="5644" />
			<Point X="240" Y="281" T="5665" />
			<Point X="241" Y="282" T="5685" />
			<Point X="242" Y="283" T="5706" />
			<Point X="243" Y="284" T="5727" />
			<Point X="244" Y="285" T="5746" />
			<Point X="244" Y="286" T="5766" />
			<Point X="245" Y="287" T="5786" />
			<Point X="245" Y="288" T="5806" />
			<Point X="245" Y="289" T="5827" />
			<Point X="246" Y="290" T="5847" />
			<Point X="246" Y="291" T="5870" />
			<Point X="247" Y="292" T="5894" />
			<Point X="248" Y="293" T="5928" />
			<Point X="249" Y="294" T="5972" />
			<Point X="249" Y="295" T="5990" />
			<Point X="249" Y="296" T="6009" />
			<Point X="250" Y="297" T="6028" />
			<Point X="250" Y="298" T="6048" />
			<Point X="251" Y="298" T="6071" />
			<Point X="252" Y="299" T="6108" />
			<Point X="252" Y="300" T="6131" />
			<Point X="252" Y="301" T="6192" />
			<Point X="253" Y="302" T="6228" />
			<Point X="254" Y="302" T="6250" />
			<Point X="254" Y="303" T="6311" />
			<Point X="254" Y="304" T="6371" />
			<Point X="255" Y="304" T="6393" />
			<Point X="255" Y="305" T="6415" />
			<Point X="256" Y="305" T="6435" />
			<Point X="257" Y="306" T="6468" />
			<Point X="257" Y="304" T="6746" />
			<Point X="257" Y="302" T="6764" />
			<Point X="257" Y="299" T="6785" />
			<Point X="257" Y="295" T="6805" />
			<Point X="257" Y="291" T="6827" />
		</Stroke>
	</Touch>
	<Touch Type="singletouch-draganddrop" StartTargetX="245" StartTargetY="75" StopTargetX="75" StopTargetY="305">
		<Stroke>
			<Point X="260" Y="80" T="17" />
			<Point X="259" Y="80" T="138" />
			<Point X="258" Y="80" T="160" />
			<Point X="257" Y="80" T="177" />
			<Point X="256" Y="80" T="197" />
			<Point X="254" Y="80" T="217" />
			<Point X="250" Y="80" T="237" />
			<Point X="249" Y="80" T="257" />
			<Point X="247" Y="80" T="281" />
			<Point X="246" Y="80" T="299" />
			<Point X="245" Y="80" T="318" />
			<Point X="244" Y="81" T="339" />
			<Point X="243" Y="82" T="359" />
			<Point X="242" Y="83" T="382" />
			<Point X="241" Y="84" T="399" />
			<Point X="239" Y="85" T="419" />
			<Point X="237" Y="86" T="440" />
			<Point X="236" Y="87" T="460" />
			<Point X="234" Y="88" T="482" />
			<Point X="233" Y="89" T="500" />
			<Point X="232" Y="91" T="520" />
			<Point X="230" Y="92" T="541" />
			<Point X="228" Y="94" T="561" />
			<Point X="224" Y="96" T="584" />
			<Point X="220" Y="98" T="602" />
			<Point X="219" Y="100" T="622" />
			<Point X="215" Y="105" T="642" />
			<Point X="214" Y="109" T="663" />
			<Point X="210" Y="113" T="683" />
			<Point X="206" Y="117" T="704" />
			<Point X="203" Y="121" T="723" />
			<Point X="200" Y="125" T="744" />
			<Point X="197" Y="128" T="763" />
			<Point X="193" Y="131" T="783" />
			<Point X="189" Y="134" T="804" />
			<Point X="188" Y="137" T="825" />
			<Point X="187" Y="140" T="844" />
			<Point X="185" Y="143" T="864" />
			<Point X="184" Y="146" T="884" />
			<Point X="182" Y="147" T="905" />
			<Point X="180" Y="151" T="928" />
			<Point X="179" Y="152" T="945" />
			<Point X="177" Y="153" T="965" />
			<Point X="176" Y="154" T="986" />
			<Point X="175" Y="155" T="1006" />
			<Point X="173" Y="156" T="1026" />
			<Point X="172" Y="157" T="1047" />
			<Point X="170" Y="159" T="1067" />
			<Point X="169" Y="160" T="1087" />
			<Point X="168" Y="162" T="1107" />
			<Point X="166" Y="163" T="1130" />
			<Point X="165" Y="165" T="1148" />
			<Point X="164" Y="166" T="1168" />
			<Point X="163" Y="167" T="1188" />
			<Point X="162" Y="169" T="1209" />
			<Point X="161" Y="170" T="1233" />
			<Point X="157" Y="172" T="1250" />
			<Point X="156" Y="173" T="1269" />
			<Point X="155" Y="174" T="1289" />
			<Point X="154" Y="175" T="1310" />
			<Point X="153" Y="176" T="1332" />
			<Point X="152" Y="177" T="1350" />
			<Point X="151" Y="178" T="1371" />
			<Point X="150" Y="179" T="1396" />
			<Point X="150" Y="180" T="1413" />
			<Point X="149" Y="181" T="1431" />
			<Point X="148" Y="182" T="1452" />
			<Point X="148" Y="183" T="1473" />
			<Point X="147" Y="184" T="1492" />
			<Point X="146" Y="185" T="1512" />
			<Point X="146" Y="186" T="1535" />
			<Point X="145" Y="187" T="1553" />
			<Point X="144" Y="188" T="1573" />
			<Point X="144" Y="189" T="1593" />
			<Point X="143" Y="190" T="1614" />
			<Point X="142" Y="191" T="1634" />
			<Point X="141" Y="192" T="1654" />
			<Point X="140" Y="192" T="1674" />
			<Point X="139" Y="193" T="1702" />
			<Point X="138" Y="193" T="1736" />
			<Point X="137" Y="194" T="1754" />
			<Point X="136" Y="194" T="1775" />
			<Point X="135" Y="194" T="1795" />
			<Point X="135" Y="195" T="1816" />
			<Point X="134" Y="195" T="1836" />
			<Point X="134" Y="196" T="1856" />
			<Point X="133" Y="196" T="1876" />
			<Point X="133" Y="197" T="1896" />
			<Point X="133" Y="198" T="1917" />
			<Point X="132" Y="198" T="1938" />
			<Point X="132" Y="199" T="1957" />
			<Point X="131" Y="200" T="1980" />
			<Point X="130" Y="200" T="1998" />
			<Point X="130" Y="201" T="2019" />
			<Point X="129" Y="201" T="2038" />
			<Point X="129" Y="202" T="2058" />
			<Point X="128" Y="202" T="2082" />
			<Point X="127" Y="203" T="2099" />
			<Point X="127" Y="204" T="2119" />
			<Point X="126" Y="204" T="2140" />
			<Point X="126" Y="205" T="2160" />
			<Point X="125" Y="205" T="2182" />
			<Point X="125" Y="206" T="2200" />
			<Point X="124" Y="206" T="2220" />
			<Point X="123" Y="207" T="2241" />
			<Point X="123" Y="208" T="2282" />
			<Point X="122" Y="208" T="2301" />
			<Point X="121" Y="209" T="2322" />
			<Point X="121" Y="210" T="2341" />
			<Point X="120" Y="210" T="2362" />
			<Point X="120" Y="211" T="2382" />
			<Point X="119" Y="212" T="2403" />
			<Point X="119" Y="213" T="2422" />
			<Point X="118" Y="214" T="2443" />
			<Point X="118" Y="215" T="2463" />
			<Point X="117" Y="216" T="2484" />
			<Point X="117" Y="217" T="2504" />
			<Point X="116" Y="218" T="2524" />
			<Point X="116" Y="219" T="2544" />
			<Point X="115" Y="220" T="2565" />
			<Point X="115" Y="221" T="2590" />
			<Point X="115" Y="222" T="2614" />
			<Point X="114" Y="223" T="2644" />
			<Point X="113" Y="224" T="2668" />
			<Point X="112" Y="225" T="2689" />
			<Point X="111" Y="226" T="2713" />
			<Point X="110" Y="227" T="2741" />
			<Point X="109" Y="228" T="2766" />
			<Point X="108" Y="229" T="2794" />
			<Point X="107" Y="230" T="2818" />
			<Point X="104" Y="231" T="2844" />
			<Point X="103" Y="232" T="2870" />
			<Point X="102" Y="233" T="2897" />
			<Point X="101" Y="234" T="2922" />
			<Point X="101" Y="235" T="2948" />
			<Point X="100" Y="236" T="2976" />
			<Point X="99" Y="237" T="3000" />
			<Point X="98" Y="238" T="3029" />
			<Point X="98" Y="239" T="3052" />
			<Point X="97" Y="241" T="3081" />
			<Point X="96" Y="243" T="3105" />
			<Point X="96" Y="244" T="3132" />
			<Point X="96" Y="245" T="3157" />
			<Point X="95" Y="246" T="3185" />
			<Point X="94" Y="247" T="3210" />
			<Point X="94" Y="249" T="3238" />
			<Point X="94" Y="251" T="3263" />
			<Point X="93" Y="252" T="3291" />
			<Point X="93" Y="253" T="3316" />
			<Point X="92" Y="254" T="3345" />
			<Point X="91" Y="255" T="3370" />
			<Point X="90" Y="256" T="3399" />
			<Point X="89" Y="257" T="3427" />
			<Point X="89" Y="258" T="3451" />
			<Point X="88" Y="259" T="3481" />
			<Point X="87" Y="260" T="3505" />
			<Point X="87" Y="262" T="3533" />
			<Point X="86" Y="263" T="3558" />
			<Point X="86" Y="265" T="3586" />
			<Point X="86" Y="267" T="3611" />
			<Point X="85" Y="272" T="3638" />
			<Point X="85" Y="273" T="3662" />
			<Point X="84" Y="274" T="3689" />
			<Point X="84" Y="275" T="3713" />
			<Point X="84" Y="277" T="3738" />
			<Point X="83" Y="279" T="3763" />
			<Point X="82" Y="280" T="3790" />
			<Point X="81" Y="281" T="3813" />
			<Point X="80" Y="282" T="3840" />
			<Point X="79" Y="283" T="3864" />
			<Point X="78" Y="284" T="3891" />
			<Point X="78" Y="285" T="3916" />
			<Point X="78" Y="286" T="3943" />
			<Point X="77" Y="287" T="3967" />
			<Point X="77" Y="287" T="3993" />
			<Point X="76" Y="288" T="4034" />
			<Point X="76" Y="289" T="4051" />
			<Point X="75" Y="290" T="4070" />
			<Point X="75" Y="291" T="4096" />
			<Point X="75" Y="292" T="4121" />
			<Point X="75" Y="293" T="4149" />
			<Point X="74" Y="294" T="4172" />
			<Point X="74" Y="295" T="4197" />
			<Point X="74" Y="295" T="4228" />
			<Point X="74" Y="295" T="4254" />
			<Point X="74" Y="295" T="4285" />
			<Point X="74" Y="295" T="4312" />
			<Point X="74" Y="295" T="4343" />
			<Point X="74" Y="295" T="4370" />
			<Point X="74" Y="295" T="4401" />
			<Point X="74" Y="295" T="4431" />
			<Point X="74" Y="295" T="4457" />
			<Point X="74" Y="295" T="4488" />
			<Point X="74" Y="295" T="4545" />
			<Point X="74" Y="295" T="4686" />
			<Point X="74" Y="295" T="4712" />
			<Point X="74" Y="295" T="4742" />
			<Point X="74" Y="295" T="4770" />
			<Point X="74" Y="295" T="4801" />
			<Point X="74" Y="295" T="4828" />
			<Point X="74" Y="295" T="4859" />
			<Point X="74" Y="295" T="4890" />
			<Point X="74" Y="295" T="4916" />
			<Point X="74" Y="295" T="4947" />
			<Point X="74" Y="295" T="4975" />
			<Point X="74" Y="295" T="5006" />
			<Point X="74" Y="295" T="5037" />
			<Point X="74" Y="295" T="5074" />
			<Point X="74" Y="295" T="5107" />
			<Point X="74" Y="295" T="5124" />
			<Point X="74" Y="295" T="5154" />
			<Point X="74" Y="295" T="5186" />
			<Point X="74" Y="295" T="5214" />
			<Point X="74" Y="295" T="5243" />
			<Point X="74" Y="295" T="5268" />
			<Point X="74" Y="295" T="5296" />
			<Point X="74" Y="295" T="5662" />
			<Point X="74" Y="295" T="5691" />
			<Point X="74" Y="295" T="5710" />
			<Point X="74" Y="295" T="5729" />
			<Point X="74" Y="295" T="5750" />
			<Point X="74" Y="295" T="5770" />
			<Point X="74" Y="295" T="5791" />
			<Point X="74" Y="295" T="5812" />
			<Point X="74" Y="295" T="5833" />
			<Point X="74" Y="295" T="5853" />
			<Point X="74" Y="295" T="5875" />
			<Point X="74" Y="295" T="6379" />
			<Point X="74" Y="295" T="6397" />
			<Point X="74" Y="295" T="6417" />
			<Point X="74" Y="295" T="6458" />
			<Point X="74" Y="295" T="6521" />
			<Point X="74" Y="295" T="6579" />
			<Point X="74" Y="295" T="6627" />
			<Point X="74" Y="295" T="6652" />
			<Point X="74" Y="295" T="7059" />
			<Point X="74" Y="295" T="7085" />
			<Point X="74" Y="295" T="7233" />
			<Point X="74" Y="295" T="7497" />
			<Point X="74" Y="295" T="7524" />
			<Point X="74" Y="295" T="7556" />
			<Point X="74" Y="295" T="7584" />
			<Point X="74" Y="295" T="7610" />
			<Point X="74" Y="295" T="7634" />
			<Point X="74" Y="295" T="7681" />
			<Point X="74" Y="295" T="7702" />
			<Point X="74" Y="295" T="7721" />
			<Point X="74" Y="295" T="7742" />
			<Point X="74" Y="295" T="7763" />
			<Point X="74" Y="295" T="7783" />
			<Point X="74" Y="295" T="7805" />
			<Point X="74" Y="295" T="7824" />
		</Stroke>
	</Touch>
	<Touch Type="singletouch-draganddrop" StartTargetX="245" StartTargetY="305" StopTargetX="75" StopTargetY="75">
		<Stroke>
			<Point X="261" Y="324" T="118" />
			<Point X="261" Y="322" T="136" />
			<Point X="261" Y="321" T="157" />
			<Point X="260" Y="318" T="177" />
			<Point X="259" Y="315" T="197" />
			<Point X="258" Y="314" T="221" />
			<Point X="257" Y="310" T="239" />
			<Point X="257" Y="309" T="258" />
			<Point X="257" Y="308" T="279" />
			<Point X="257" Y="306" T="298" />
			<Point X="257" Y="305" T="321" />
			<Point X="257" Y="304" T="339" />
			<Point X="257" Y="302" T="360" />
			<Point X="257" Y="301" T="379" />
			<Point X="257" Y="300" T="400" />
			<Point X="257" Y="299" T="420" />
			<Point X="257" Y="298" T="441" />
			<Point X="256" Y="298" T="582" />
			<Point X="255" Y="297" T="599" />
			<Point X="251" Y="296" T="619" />
			<Point X="250" Y="295" T="640" />
			<Point X="249" Y="294" T="663" />
			<Point X="247" Y="292" T="683" />
			<Point X="245" Y="290" T="703" />
			<Point X="243" Y="286" T="723" />
			<Point X="241" Y="285" T="744" />
			<Point X="239" Y="281" T="764" />
			<Point X="235" Y="277" T="784" />
			<Point X="234" Y="273" T="804" />
			<Point X="230" Y="269" T="824" />
			<Point X="226" Y="265" T="844" />
			<Point X="222" Y="262" T="865" />
			<Point X="218" Y="258" T="885" />
			<Point X="214" Y="253" T="905" />
			<Point X="210" Y="248" T="925" />
			<Point X="207" Y="244" T="946" />
			<Point X="206" Y="240" T="969" />
			<Point X="205" Y="239" T="987" />
			<Point X="201" Y="235" T="1006" />
			<Point X="200" Y="232" T="1027" />
			<Point X="199" Y="231" T="1047" />
			<Point X="197" Y="227" T="1071" />
			<Point X="193" Y="223" T="1088" />
			<Point X="192" Y="219" T="1108" />
			<Point X="188" Y="215" T="1128" />
			<Point X="184" Y="211" T="1149" />
			<Point X="180" Y="207" T="1171" />
			<Point X="177" Y="203" T="1189" />
			<Point X="173" Y="199" T="1209" />
			<Point X="170" Y="195" T="1230" />
			<Point X="169" Y="191" T="1249" />
			<Point X="165" Y="187" T="1288" />
			<Point X="164" Y="184" T="1309" />
			<Point X="163" Y="183" T="1326" />
			<Point X="162" Y="182" T="1345" />
			<Point X="161" Y="181" T="1366" />
			<Point X="160" Y="180" T="1382" />
			<Point X="159" Y="178" T="1403" />
			<Point X="158" Y="176" T="1420" />
			<Point X="156" Y="175" T="1436" />
			<Point X="155" Y="173" T="1455" />
			<Point X="151" Y="171" T="1476" />
			<Point X="147" Y="166" T="1495" />
			<Point X="146" Y="165" T="1518" />
			<Point X="145" Y="163" T="1536" />
			<Point X="143" Y="161" T="1557" />
			<Point X="142" Y="157" T="1576" />
			<Point X="140" Y="156" T="1597" />
			<Point X="138" Y="154" T="1620" />
			<Point X="136" Y="150" T="1638" />
			<Point X="134" Y="149" T="1657" />
			<Point X="133" Y="147" T="1678" />
			<Point X="131" Y="143" T="1698" />
			<Point X="130" Y="139" T="1722" />
			<Point X="128" Y="138" T="1738" />
			<Point X="126" Y="137" T="1759" />
			<Point X="124" Y="135" T="1779" />
			<Point X="123" Y="133" T="1800" />
			<Point X="122" Y="131" T="1821" />
			<Point X="121" Y="129" T="1840" />
			<Point X="119" Y="127" T="1860" />
			<Point X="117" Y="125" T="1881" />
			<Point X="116" Y="124" T="1901" />
			<Point X="114" Y="122" T="1921" />
			<Point X="113" Y="120" T="1941" />
			<Point X="112" Y="118" T="1961" />
			<Point X="111" Y="116" T="1982" />
			<Point X="110" Y="115" T="2002" />
			<Point X="109" Y="113" T="2023" />
			<Point X="108" Y="112" T="2043" />
			<Point X="107" Y="110" T="2063" />
			<Point X="106" Y="109" T="2083" />
			<Point X="105" Y="107" T="2104" />
			<Point X="104" Y="105" T="2124" />
			<Point X="103" Y="104" T="2144" />
			<Point X="102" Y="102" T="2164" />
			<Point X="101" Y="100" T="2189" />
			<Point X="100" Y="98" T="2206" />
			<Point X="99" Y="97" T="2225" />
			<Point X="97" Y="96" T="2245" />
			<Point X="96" Y="94" T="2269" />
			<Point X="95" Y="92" T="2287" />
			<Point X="94" Y="91" T="2306" />
			<Point X="92" Y="89" T="2326" />
			<Point X="91" Y="87" T="2347" />
			<Point X="90" Y="86" T="2371" />
			<Point X="89" Y="84" T="2387" />
			<Point X="88" Y="83" T="2407" />
			<Point X="87" Y="82" T="2428" />
			<Point X="86" Y="81" T="2448" />
			<Point X="85" Y="80" T="2471" />
			<Point X="84" Y="79" T="2489" />
			<Point X="83" Y="78" T="2509" />
			<Point X="82" Y="77" T="2529" />
			<Point X="81" Y="76" T="2549" />
			<Point X="80" Y="75" T="2571" />
			<Point X="80" Y="74" T="2591" />
			<Point X="79" Y="73" T="2610" />
			<Point X="78" Y="72" T="2630" />
			<Point X="78" Y="71" T="2651" />
			<Point X="78" Y="70" T="2672" />
			<Point X="77" Y="69" T="2691" />
			<Point X="77" Y="68" T="2712" />
			<Point X="76" Y="64" T="2738" />
			<Point X="75" Y="63" T="2768" />
			<Point X="75" Y="62" T="2846" />
			<Point X="75" Y="62" T="3241" />
			<Point X="75" Y="62" T="3269" />
			<Point X="75" Y="63" T="3292" />
			<Point X="75" Y="63" T="3320" />
			<Point X="74" Y="63" T="3350" />
			<Point X="74" Y="63" T="3380" />
			<Point X="74" Y="63" T="3410" />
			<Point X="74" Y="64" T="3441" />
			<Point X="74" Y="65" T="3472" />
			<Point X="74" Y="66" T="3498" />
			<Point X="74" Y="67" T="3529" />
			<Point X="74" Y="68" T="3557" />
			<Point X="74" Y="68" T="3587" />
			<Point X="74" Y="68" T="3617" />
			<Point X="74" Y="69" T="3643" />
			<Point X="74" Y="69" T="3673" />
			<Point X="74" Y="70" T="3701" />
			<Point X="74" Y="71" T="3732" />
			<Point X="74" Y="72" T="3759" />
			<Point X="74" Y="73" T="3790" />
			<Point X="74" Y="73" T="3820" />
			<Point X="74" Y="73" T="3846" />
			<Point X="74" Y="73" T="3886" />
			<Point X="74" Y="73" T="4411" />
			<Point X="77" Y="73" T="4547" />
			<Point X="78" Y="73" T="4730" />
			<Point X="80" Y="73" T="5203" />
			<Point X="80" Y="73" T="5371" />
			<Point X="80" Y="73" T="5401" />
			<Point X="80" Y="73" T="5455" />
			<Point X="80" Y="73" T="5508" />
			<Point X="80" Y="73" T="5536" />
			<Point X="79" Y="73" T="5562" />
			<Point X="79" Y="73" T="5590" />
			<Point X="79" Y="73" T="5616" />
			<Point X="79" Y="73" T="5671" />
			<Point X="79" Y="73" T="5697" />
			<Point X="78" Y="73" T="5727" />
			<Point X="78" Y="73" T="5751" />
			<Point X="77" Y="73" T="5781" />
			<Point X="77" Y="72" T="5819" />
			<Point X="76" Y="72" T="5839" />
			<Point X="76" Y="71" T="5860" />
			<Point X="75" Y="71" T="5901" />
			<Point X="74" Y="70" T="6001" />
			<Point X="74" Y="69" T="6101" />
			<Point X="73" Y="69" T="6122" />
			<Point X="73" Y="68" T="6199" />
			<Point X="72" Y="68" T="6279" />
			<Point X="72" Y="67" T="6378" />
			<Point X="71" Y="67" T="6476" />
			<Point X="71" Y="66" T="6555" />
			<Point X="71" Y="65" T="6615" />
		</Stroke>
	</Touch>
	<Touch Type="singletouch-draganddrop" StartTargetX="75" StartTargetY="305" StopTargetX="245" StopTargetY="75">
		<Stroke>
			<Point X="77" Y="334" T="185" />
			<Point X="77" Y="334" T="205" />
			<Point X="77" Y="334" T="246" />
			<Point X="77" Y="333" T="357" />
			<Point X="77" Y="330" T="386" />
			<Point X="77" Y="329" T="410" />
			<Point X="77" Y="328" T="439" />
			<Point X="77" Y="327" T="462" />
			<Point X="77" Y="326" T="491" />
			<Point X="78" Y="326" T="594" />
			<Point X="79" Y="326" T="632" />
			<Point X="79" Y="325" T="725" />
			<Point X="79" Y="324" T="829" />
			<Point X="80" Y="323" T="853" />
			<Point X="80" Y="322" T="879" />
			<Point X="80" Y="321" T="907" />
			<Point X="80" Y="320" T="934" />
			<Point X="81" Y="320" T="957" />
			<Point X="81" Y="319" T="986" />
			<Point X="81" Y="318" T="1009" />
			<Point X="82" Y="317" T="1038" />
			<Point X="83" Y="316" T="1062" />
			<Point X="83" Y="315" T="1091" />
			<Point X="83" Y="314" T="1114" />
			<Point X="84" Y="313" T="1142" />
			<Point X="85" Y="312" T="1166" />
			<Point X="86" Y="311" T="1193" />
			<Point X="87" Y="310" T="1218" />
			<Point X="87" Y="310" T="1245" />
			<Point X="88" Y="309" T="1270" />
			<Point X="88" Y="308" T="1296" />
			<Point X="88" Y="308" T="1322" />
			<Point X="88" Y="307" T="1349" />
			<Point X="88" Y="307" T="1374" />
			<Point X="92" Y="307" T="1411" />
			<Point X="92" Y="307" T="1420" />
			<Point X="92" Y="306" T="1437" />
			<Point X="92" Y="305" T="1455" />
			<Point X="92" Y="304" T="1475" />
			<Point X="92" Y="303" T="1496" />
			<Point X="92" Y="302" T="1516" />
			<Point X="92" Y="301" T="1539" />
			<Point X="93" Y="301" T="1576" />
			<Point X="93" Y="300" T="1627" />
			<Point X="94" Y="299" T="1644" />
			<Point X="95" Y="299" T="1657" />
			<Point X="96" Y="298" T="1677" />
			<Point X="96" Y="297" T="1716" />
			<Point X="97" Y="296" T="1740" />
			<Point X="98" Y="295" T="1757" />
			<Point X="99" Y="294" T="1777" />
			<Point X="100" Y="293" T="1797" />
			<Point X="100" Y="292" T="1818" />
			<Point X="101" Y="291" T="1840" />
			<Point X="102" Y="289" T="1858" />
			<Point X="103" Y="287" T="1879" />
			<Point X="104" Y="285" T="1899" />
			<Point X="109" Y="283" T="1919" />
			<Point X="113" Y="276" T="1940" />
			<Point X="119" Y="268" T="1960" />
			<Point X="126" Y="260" T="1989" />
			<Point X="132" Y="252" T="2013" />
			<Point X="137" Y="247" T="2042" />
			<Point X="137" Y="245" T="2068" />
			<Point X="138" Y="244" T="2096" />
			<Point X="139" Y="243" T="2122" />
			<Point X="139" Y="242" T="2150" />
			<Point X="139" Y="241" T="2176" />
			<Point X="139" Y="240" T="2204" />
			<Point X="139" Y="240" T="2229" />
			<Point X="140" Y="239" T="2258" />
			<Point X="140" Y="238" T="2312" />
			<Point X="140" Y="238" T="2339" />
			<Point X="140" Y="237" T="2363" />
			<Point X="140" Y="237" T="2392" />
			<Point X="141" Y="236" T="2417" />
			<Point X="141" Y="235" T="2456" />
			<Point X="141" Y="234" T="2463" />
			<Point X="142" Y="233" T="2479" />
			<Point X="142" Y="232" T="2497" />
			<Point X="142" Y="231" T="2518" />
			<Point X="142" Y="230" T="2539" />
			<Point X="143" Y="229" T="2558" />
			<Point X="143" Y="228" T="2579" />
			<Point X="144" Y="227" T="2599" />
			<Point X="145" Y="226" T="2622" />
			<Point X="146" Y="226" T="2639" />
			<Point X="147" Y="226" T="2699" />
			<Point X="147" Y="225" T="2722" />
			<Point X="147" Y="224" T="2739" />
			<Point X="148" Y="223" T="2779" />
			<Point X="149" Y="222" T="2821" />
			<Point X="149" Y="221" T="2859" />
			<Point X="149" Y="220" T="2881" />
			<Point X="150" Y="219" T="2900" />
			<Point X="151" Y="219" T="2920" />
			<Point X="152" Y="218" T="2940" />
			<Point X="153" Y="217" T="2981" />
			<Point X="154" Y="216" T="3022" />
			<Point X="155" Y="215" T="3042" />
			<Point X="156" Y="214" T="3082" />
			<Point X="157" Y="213" T="3121" />
			<Point X="157" Y="212" T="3142" />
			<Point X="158" Y="211" T="3160" />
			<Point X="159" Y="210" T="3191" />
			<Point X="160" Y="209" T="3208" />
			<Point X="160" Y="208" T="3228" />
			<Point X="161" Y="207" T="3250" />
			<Point X="162" Y="206" T="3268" />
			<Point X="163" Y="204" T="3284" />
			<Point X="164" Y="203" T="3302" />
			<Point X="165" Y="202" T="3322" />
			<Point X="165" Y="201" T="3343" />
			<Point X="166" Y="200" T="3363" />
			<Point X="166" Y="199" T="3383" />
			<Point X="167" Y="198" T="3403" />
			<Point X="167" Y="197" T="3426" />
			<Point X="167" Y="195" T="3444" />
			<Point X="168" Y="194" T="3464" />
			<Point X="168" Y="193" T="3484" />
			<Point X="168" Y="192" T="3505" />
			<Point X="168" Y="191" T="3528" />
			<Point X="169" Y="190" T="3545" />
			<Point X="170" Y="189" T="3565" />
			<Point X="171" Y="188" T="3586" />
			<Point X="172" Y="187" T="3606" />
			<Point X="172" Y="186" T="3626" />
			<Point X="173" Y="185" T="3646" />
			<Point X="174" Y="184" T="3667" />
			<Point X="174" Y="183" T="3687" />
			<Point X="175" Y="182" T="3707" />
			<Point X="175" Y="181" T="3729" />
			<Point X="176" Y="180" T="3748" />
			<Point X="176" Y="179" T="3768" />
			<Point X="177" Y="178" T="3788" />
			<Point X="177" Y="177" T="3809" />
			<Point X="178" Y="176" T="3830" />
			<Point X="178" Y="175" T="3849" />
			<Point X="178" Y="174" T="3869" />
			<Point X="178" Y="173" T="3890" />
			<Point X="179" Y="172" T="3910" />
			<Point X="179" Y="171" T="3932" />
			<Point X="180" Y="170" T="3950" />
			<Point X="181" Y="169" T="3971" />
			<Point X="182" Y="168" T="3991" />
			<Point X="183" Y="167" T="4011" />
			<Point X="183" Y="166" T="4031" />
			<Point X="184" Y="165" T="4052" />
			<Point X="185" Y="164" T="4075" />
			<Point X="186" Y="163" T="4092" />
			<Point X="187" Y="161" T="4112" />
			<Point X="187" Y="159" T="4133" />
			<Point X="188" Y="158" T="4153" />
			<Point X="188" Y="156" T="4176" />
			<Point X="189" Y="154" T="4200" />
			<Point X="190" Y="150" T="4229" />
			<Point X="191" Y="149" T="4252" />
			<Point X="192" Y="147" T="4280" />
			<Point X="193" Y="143" T="4305" />
			<Point X="194" Y="142" T="4332" />
			<Point X="195" Y="140" T="4357" />
			<Point X="196" Y="138" T="4384" />
			<Point X="197" Y="137" T="4409" />
			<Point X="198" Y="136" T="4437" />
			<Point X="199" Y="134" T="4462" />
			<Point X="200" Y="132" T="4489" />
			<Point X="201" Y="130" T="4525" />
			<Point X="202" Y="128" T="4533" />
			<Point X="203" Y="126" T="4550" />
			<Point X="204" Y="124" T="4569" />
			<Point X="204" Y="122" T="4589" />
			<Point X="204" Y="121" T="4610" />
			<Point X="204" Y="119" T="4631" />
			<Point X="204" Y="118" T="4650" />
			<Point X="205" Y="117" T="4670" />
			<Point X="206" Y="116" T="4690" />
			<Point X="207" Y="115" T="4711" />
			<Point X="208" Y="114" T="4731" />
			<Point X="210" Y="113" T="4751" />
			<Point X="212" Y="112" T="4774" />
			<Point X="214" Y="111" T="4791" />
			<Point X="215" Y="110" T="4812" />
			<Point X="216" Y="108" T="4832" />
			<Point X="217" Y="106" T="4852" />
			<Point X="218" Y="105" T="4875" />
			<Point X="219" Y="103" T="4893" />
			<Point X="220" Y="102" T="4913" />
			<Point X="221" Y="101" T="4933" />
			<Point X="222" Y="99" T="4954" />
			<Point X="223" Y="98" T="4977" />
			<Point X="224" Y="97" T="4994" />
			<Point X="225" Y="96" T="5014" />
			<Point X="226" Y="95" T="5035" />
			<Point X="227" Y="94" T="5055" />
			<Point X="228" Y="93" T="5078" />
			<Point X="229" Y="92" T="5095" />
			<Point X="230" Y="91" T="5116" />
			<Point X="231" Y="90" T="5138" />
			<Point X="232" Y="89" T="5160" />
			<Point X="233" Y="88" T="5180" />
			<Point X="235" Y="87" T="5200" />
			<Point X="236" Y="86" T="5222" />
			<Point X="238" Y="85" T="5239" />
			<Point X="239" Y="84" T="5257" />
			<Point X="240" Y="83" T="5278" />
			<Point X="241" Y="82" T="5298" />
			<Point X="242" Y="81" T="5318" />
			<Point X="243" Y="80" T="5340" />
			<Point X="244" Y="79" T="5359" />
			<Point X="245" Y="78" T="5379" />
			<Point X="246" Y="78" T="5399" />
			<Point X="247" Y="77" T="5419" />
			<Point X="248" Y="76" T="5441" />
			<Point X="249" Y="76" T="5460" />
			<Point X="250" Y="75" T="5480" />
			<Point X="251" Y="75" T="5500" />
			<Point X="252" Y="75" T="5521" />
			<Point X="253" Y="74" T="5541" />
			<Point X="254" Y="74" T="5584" />
			<Point X="255" Y="73" T="5622" />
			<Point X="256" Y="73" T="5684" />
			<Point X="256" Y="72" T="5764" />
			<Point X="256" Y="71" T="5782" />
			<Point X="256" Y="70" T="5802" />
			<Point X="256" Y="69" T="5842" />
			<Point X="256" Y="68" T="5885" />
			<Point X="256" Y="67" T="5903" />
			<Point X="256" Y="66" T="6006" />
		</Stroke>
	</Touch>
	<Touch Type="singletouch-draganddrop" StartTargetX="245" StartTargetY="75" StopTargetX="75" StopTargetY="305">
		<Stroke>
			<Point X="277" Y="69" T="18" />
			<Point X="276" Y="69" T="39" />
			<Point X="275" Y="69" T="59" />
			<Point X="274" Y="69" T="80" />
			<Point X="273" Y="69" T="100" />
			<Point X="272" Y="69" T="121" />
			<Point X="271" Y="69" T="141" />
			<Point X="270" Y="70" T="161" />
			<Point X="269" Y="70" T="184" />
			<Point X="268" Y="71" T="202" />
			<Point X="267" Y="71" T="222" />
			<Point X="266" Y="71" T="242" />
			<Point X="265" Y="71" T="262" />
			<Point X="264" Y="71" T="287" />
			<Point X="263" Y="72" T="304" />
			<Point X="262" Y="72" T="323" />
			<Point X="261" Y="72" T="343" />
			<Point X="260" Y="73" T="364" />
			<Point X="259" Y="73" T="387" />
			<Point X="258" Y="74" T="404" />
			<Point X="257" Y="74" T="424" />
			<Point X="256" Y="74" T="445" />
			<Point X="255" Y="74" T="465" />
			<Point X="253" Y="74" T="487" />
			<Point X="252" Y="75" T="505" />
			<Point X="250" Y="76" T="526" />
			<Point X="249" Y="76" T="546" />
			<Point X="247" Y="77" T="566" />
			<Point X="246" Y="78" T="586" />
			<Point X="245" Y="79" T="607" />
			<Point X="244" Y="80" T="627" />
			<Point X="243" Y="81" T="647" />
			<Point X="242" Y="86" T="667" />
			<Point X="241" Y="90" T="690" />
			<Point X="240" Y="94" T="708" />
			<Point X="239" Y="98" T="728" />
			<Point X="238" Y="101" T="748" />
			<Point X="237" Y="102" T="769" />
			<Point X="232" Y="103" T="789" />
			<Point X="228" Y="107" T="809" />
			<Point X="224" Y="111" T="830" />
			<Point X="223" Y="115" T="850" />
			<Point X="222" Y="118" T="870" />
			<Point X="221" Y="122" T="890" />
			<Point X="220" Y="125" T="911" />
			<Point X="216" Y="128" T="935" />
			<Point X="215" Y="128" T="959" />
			<Point X="214" Y="129" T="977" />
			<Point X="213" Y="130" T="998" />
			<Point X="212" Y="131" T="1018" />
			<Point X="211" Y="136" T="1038" />
			<Point X="210" Y="137" T="1054" />
			<Point X="209" Y="138" T="1073" />
			<Point X="208" Y="139" T="1093" />
			<Point X="207" Y="140" T="1113" />
			<Point X="206" Y="141" T="1136" />
			<Point X="206" Y="143" T="1154" />
			<Point X="205" Y="144" T="1174" />
			<Point X="205" Y="146" T="1194" />
			<Point X="205" Y="147" T="1214" />
			<Point X="204" Y="148" T="1238" />
			<Point X="203" Y="149" T="1256" />
			<Point X="203" Y="150" T="1275" />
			<Point X="202" Y="151" T="1295" />
			<Point X="201" Y="152" T="1316" />
			<Point X="200" Y="153" T="1337" />
			<Point X="199" Y="154" T="1356" />
			<Point X="198" Y="159" T="1376" />
			<Point X="197" Y="160" T="1398" />
			<Point X="196" Y="161" T="1416" />
			<Point X="195" Y="162" T="1437" />
			<Point X="194" Y="163" T="1457" />
			<Point X="193" Y="165" T="1478" />
			<Point X="192" Y="167" T="1497" />
			<Point X="191" Y="172" T="1518" />
			<Point X="190" Y="173" T="1538" />
			<Point X="190" Y="174" T="1559" />
			<Point X="189" Y="176" T="1579" />
			<Point X="188" Y="177" T="1599" />
			<Point X="187" Y="179" T="1620" />
			<Point X="186" Y="180" T="1640" />
			<Point X="185" Y="181" T="1659" />
			<Point X="184" Y="182" T="1680" />
			<Point X="183" Y="183" T="1701" />
			<Point X="182" Y="184" T="1721" />
			<Point X="181" Y="185" T="1741" />
			<Point X="180" Y="186" T="1761" />
			<Point X="180" Y="188" T="1784" />
			<Point X="179" Y="189" T="1801" />
			<Point X="179" Y="194" T="1822" />
			<Point X="179" Y="195" T="1842" />
			<Point X="178" Y="196" T="1864" />
			<Point X="178" Y="197" T="1882" />
			<Point X="178" Y="198" T="1903" />
			<Point X="178" Y="199" T="1923" />
			<Point X="177" Y="200" T="1944" />
			<Point X="176" Y="201" T="1964" />
			<Point X="175" Y="202" T="1987" />
			<Point X="174" Y="203" T="2004" />
			<Point X="173" Y="204" T="2025" />
			<Point X="172" Y="205" T="2044" />
			<Point X="171" Y="207" T="2065" />
			<Point X="171" Y="208" T="2087" />
			<Point X="170" Y="209" T="2106" />
			<Point X="169" Y="210" T="2125" />
			<Point X="168" Y="212" T="2146" />
			<Point X="167" Y="213" T="2166" />
			<Point X="166" Y="214" T="2189" />
			<Point X="165" Y="216" T="2206" />
			<Point X="164" Y="217" T="2227" />
			<Point X="163" Y="219" T="2247" />
			<Point X="162" Y="221" T="2268" />
			<Point X="161" Y="223" T="2287" />
			<Point X="160" Y="228" T="2308" />
			<Point X="158" Y="229" T="2328" />
			<Point X="157" Y="230" T="2349" />
			<Point X="155" Y="232" T="2369" />
			<Point X="153" Y="234" T="2389" />
			<Point X="152" Y="236" T="2409" />
			<Point X="151" Y="242" T="2430" />
			<Point X="150" Y="246" T="2450" />
			<Point X="149" Y="250" T="2470" />
			<Point X="148" Y="254" T="2491" />
			<Point X="147" Y="257" T="2511" />
			<Point X="145" Y="260" T="2531" />
			<Point X="144" Y="261" T="2551" />
			<Point X="140" Y="265" T="2571" />
			<Point X="139" Y="269" T="2592" />
			<Point X="138" Y="272" T="2612" />
			<Point X="134" Y="275" T="2635" />
			<Point X="133" Y="276" T="2652" />
			<Point X="132" Y="280" T="2672" />
			<Point X="130" Y="281" T="2692" />
			<Point X="128" Y="285" T="2713" />
			<Point X="126" Y="285" T="2737" />
			<Point X="125" Y="286" T="2754" />
			<Point X="124" Y="287" T="2773" />
			<Point X="123" Y="288" T="2794" />
			<Point X="122" Y="289" T="2814" />
			<Point X="121" Y="290" T="2837" />
			<Point X="120" Y="291" T="2854" />
			<Point X="118" Y="292" T="2875" />
			<Point X="116" Y="292" T="2895" />
			<Point X="115" Y="292" T="2915" />
			<Point X="114" Y="293" T="2937" />
			<Point X="112" Y="294" T="2956" />
			<Point X="111" Y="294" T="2976" />
			<Point X="109" Y="295" T="2996" />
			<Point X="107" Y="295" T="3016" />
			<Point X="105" Y="296" T="3038" />
			<Point X="104" Y="296" T="3057" />
			<Point X="103" Y="296" T="3077" />
			<Point X="102" Y="296" T="3098" />
			<Point X="101" Y="296" T="3118" />
			<Point X="100" Y="296" T="3140" />
			<Point X="99" Y="296" T="3158" />
			<Point X="98" Y="297" T="3178" />
			<Point X="97" Y="297" T="3199" />
			<Point X="96" Y="298" T="3219" />
			<Point X="95" Y="298" T="3244" />
			<Point X="93" Y="298" T="3269" />
			<Point X="92" Y="298" T="3296" />
			<Point X="91" Y="298" T="3320" />
			<Point X="90" Y="298" T="3347" />
			<Point X="89" Y="298" T="3370" />
			<Point X="87" Y="298" T="3396" />
			<Point X="87" Y="298" T="3421" />
			<Point X="87" Y="298" T="3447" />
			<Point X="87" Y="298" T="3474" />
			<Point X="87" Y="298" T="3505" />
			<Point X="87" Y="298" T="3539" />
			<Point X="87" Y="298" T="3562" />
			<Point X="87" Y="298" T="3581" />
			<Point X="87" Y="298" T="3607" />
			<Point X="87" Y="298" T="3634" />
			<Point X="87" Y="298" T="3662" />
			<Point X="87" Y="298" T="3687" />
			<Point X="87" Y="298" T="3715" />
			<Point X="87" Y="298" T="3744" />
			<Point X="87" Y="298" T="3769" />
			<Point X="87" Y="298" T="3798" />
			<Point X="87" Y="298" T="3824" />
			<Point X="87" Y="298" T="3854" />
			<Point X="87" Y="298" T="3880" />
			<Point X="87" Y="298" T="3909" />
			<Point X="87" Y="298" T="3993" />
			<Point X="87" Y="298" T="4018" />
			<Point X="87" Y="298" T="4075" />
			<Point X="87" Y="298" T="4130" />
			<Point X="87" Y="298" T="4181" />
			<Point X="87" Y="298" T="4209" />
			<Point X="87" Y="298" T="4232" />
			<Point X="87" Y="298" T="4257" />
			<Point X="87" Y="298" T="4362" />
			<Point X="87" Y="298" T="4385" />
			<Point X="87" Y="298" T="4465" />
			<Point X="87" Y="298" T="4488" />
			<Point X="87" Y="298" T="4517" />
			<Point X="87" Y="298" T="4540" />
			<Point X="87" Y="298" T="4563" />
			<Point X="87" Y="298" T="4581" />
			<Point X="87" Y="298" T="4601" />
			<Point X="87" Y="298" T="4621" />
			<Point X="87" Y="298" T="4664" />
			<Point X="87" Y="298" T="4681" />
		</Stroke>
	</Touch>
</TouchCollection>
